__init__.py
main.py
main_stdio.py
onvif_device_manage.py
test.py
config/__init__.py
config/settings.py
managers/__init__.py
managers/token.py
services/__init__.py
services/yms_query.py
utils/__init__.py
utils/minio.py
yms_mcp-2.0.4.dist-info/licenses/LICENSE
yms_mcp-2.0.4.dist-info/METADATA
yms_mcp-2.0.4.dist-info/WHEEL
yms_mcp-2.0.4.dist-info/entry_points.txt
yms_mcp-2.0.4.dist-info/top_level.txt
yms_mcp-2.0.4.dist-info/RECORD
