Metadata-Version: 2.4
Name: yms-mcp
Version: 2.0.4
Summary: YMS MCP Server - ONVIF camera control and YMS query tools for Model Context Protocol
Requires-Python: >=3.11
License-File: LICENSE
Requires-Dist: onvif-zeep>=0.2.12
Requires-Dist: wsdiscovery
Requires-Dist: requests
Requires-Dist: minio>=7.2.0
Requires-Dist: httpx>=0.28.1
Requires-Dist: mcp[cli]>=1.6.0
Requires-Dist: openai>=1.70.0
Requires-Dist: pytz>=2025.2
Requires-Dist: uvicorn>=0.34.0
Requires-Dist: starlette>=0.46.1
Requires-Dist: pyyaml>=6.0.1
Requires-Dist: pydantic-settings>=2.6.0
Requires-Dist: python-dotenv>=1.0.1
Requires-Dist: loguru>=0.7.2
Dynamic: license-file
